tracpdf/__init__.py
tracpdf/admin.py
tracpdf/pdfbook.py
tracpdf/util.py
tracpdf/wikiprint.py
tracpdf/htdocs/css/wikiprint.css
tracpdf/templates/wikiprint_admin_parameters.html
tracpdf/templates/wikiprint_parameters.html
TracWikiPrint-4.0.0.dev0.dist-info/COPYING
TracWikiPrint-4.0.0.dev0.dist-info/METADATA
TracWikiPrint-4.0.0.dev0.dist-info/WHEEL
TracWikiPrint-4.0.0.dev0.dist-info/entry_points.txt
TracWikiPrint-4.0.0.dev0.dist-info/top_level.txt
TracWikiPrint-4.0.0.dev0.dist-info/RECORD
