Metadata-Version: 2.1
Name: TracWikiPrint
Version: 4.0.0.dev0
Summary: Create PDF files from Tracs wiki pages
Home-page: http://trac-hacks.org/wiki/TracWikiPrintPlugin
Author: Cinc-th
Author-email: 
Maintainer: Cinc-th
License: BSD
Keywords: PDF wiki trac plugin
Classifier: Development Status :: 4 - Beta
Classifier: Environment :: Plugins
Classifier: Environment :: Web Environment
Classifier: Framework :: Trac
Classifier: Intended Audience :: End Users/Desktop
Classifier: License :: OSI Approved :: BSD License
Classifier: Natural Language :: English
Classifier: Operating System :: OS Independent
Classifier: Programming Language :: Python :: 2
Classifier: Programming Language :: Python :: 2.7
Classifier: Programming Language :: Python :: 3
License-File: COPYING
Requires-Dist: pdfkit
Requires-Dist: trac
